watchmen_utilities/__init__.py
watchmen_utilities/array_helper.py
watchmen_utilities/datetime_helper.py
watchmen_utilities/event_loop_helper.py
watchmen_utilities/json_helper.py
watchmen_utilities/log_filter.py
watchmen_utilities/logger.py
watchmen_utilities/mdc.py
watchmen_utilities/numeric_helper.py
watchmen_utilities/pydantic_helper.py
watchmen_utilities/string_helper.py
watchmen_utilities/value_expression.py
watchmen_utilities-18.0.1.dist-info/METADATA
watchmen_utilities-18.0.1.dist-info/WHEEL
watchmen_utilities-18.0.1.dist-info/RECORD
